captchaai/__init__.py
captchaai/api.py
captchaai/setup.py
captchaai/solver.py
captchaai-0.0.3.dist-info/METADATA
captchaai-0.0.3.dist-info/WHEEL
captchaai-0.0.3.dist-info/licenses/LICENSE.txt
captchaai-0.0.3.dist-info/RECORD
