Metadata-Version: 2.1
Name: captchaai
Version: 0.0.3
Summary: A package to enable interacting with the api of captchaai.com by python.
Project-URL: Homepage, https://github.com/captchaai-developers/captchaai
Project-URL: Bug Tracker, https://github.com/captchaai-developers/captchaai/issues
Author-email: captchaai developers <dev@captchaai.com>
License-File: LICENSE.txt
Classifier: License :: OSI Approved :: MIT License
Classifier: Operating System :: OS Independent
Classifier: Programming Language :: Python :: 3
Requires-Python: >=3.7
